Workbook

Sheet Resumo
A1: Resumo financeiro
A2: Cenário profissional enxuto e cenários de crescimento.
A4: Premissa | B4: Valor
A5: Câmbio de referência | B5: 5.0638
A6: Data-base | B6: 24/07/2026
A8: Operação profissional enxuta
A9: Item | B9: US$/mês | C9: R$/mês
A10: Vercel Pro | B10: 20 | C10: =B10*$B$5
A11: Supabase Pro | B11: 25 | C11: =B11*$B$5
A12: WasenderAPI Basic | B12: 6 | C12: =B12*$B$5
A13: Reserva inicial de IA | B13: 10 | C13: =B13*$B$5
A14: Serper amortizado em 6 meses | B14: 8.33 | C14: =B14*$B$5
A15: Subtotal | B15: =SUM(B10:B14) | C15: =SUM(C10:C14)
A18: Cenário de IA | B18: Mínimo (US$) | C18: Máximo (US$) | D18: Mínimo (R$) | E18: Máximo (R$)
A19: Piloto | B19: 7 | C19: 12 | D19: =B19*$B$5 | E19: =C19*$B$5
A20: Crescimento | B20: 32 | C20: 48 | D20: =B20*$B$5 | E20: =C20*$B$5
A21: Escala | B21: 130 | C21: 180 | D21: =B21*$B$5 | E21: =C21*$B$5

Sheet Custos
A1: Custos do Poupaqui Ecommerce
A2: Valores de referência em 24/07/2026. Confirme os planos e faturas antes de decidir.
A4: Categoria | B4: Fornecedor | C4: Item | D4: Cobrança | E4: Referência (US$) | F4: Referência (R$) | G4: Obrigatório | H4: Responsável sugerido | I4: Observação
A5: Infraestrutura | B5: Vercel | C5: Plano Pro | D5: Mensal | E5: 20 | F5: 101.28 | G5: Sim | H5: Licence Farma | I5: Inclui crédito de uso; excedentes variáveis
A6: Dados | B6: Supabase | C6: Plano Pro recomendado | D6: Mensal | E6: 25 | F6: 126.6 | G6: Sim para produção | H6: Licence Farma | I6: Confirmar o plano atualmente contratado
A7: Mensageria | B7: WasenderAPI | C7: Basic — 1 sessão | D7: Mensal | E7: 6 | F7: 30.38 | G7: Condicional | H7: Licence Farma | I7: Confirmar o número de sessões necessárias
A8: Inteligência artificial | B8: Anthropic | C8: Reserva inicial | D8: Mensal variável | E8: 10 | F8: 50.64 | G8: Condicional | H8: Licence Farma | I8: Medir tokens por recurso
A9: Pesquisa | B9: Serper | C9: 50 mil créditos / 6 meses | D9: Compra avulsa | E9: 50 | F9: 253.19 | G9: Condicional | H9: Licence Farma | I9: Equivale a cerca de US$ 8,33/mês se distribuído em seis meses
A10: Imagens | B10: Cloudinary | C10: Free | D10: Franquia | E10: 0 | F10: 0 | G10: Condicional | H10: Licence Farma | I10: 25 créditos mensais
A11: Imagens | B11: Cloudinary | C11: Plus | D11: Mensal | E11: 99 | F11: 501.32 | G11: Opcional | H11: Licence Farma | I11: Upgrade conforme armazenamento, tráfego e transformações
A12: E-mail | B12: Resend | C12: Free | D12: Franquia | E12: 0 | F12: 0 | G12: Condicional | H12: Licence Farma | I12: 3.000 e-mails/mês e limite de 100/dia
A13: E-mail | B13: Resend | C13: Pro | D13: Mensal | E13: 20 | F13: 101.28 | G13: Opcional | H13: Licence Farma | I13: 50 mil e-mails mensais
A14: OCR | B14: OCR.space | C14: Free | D14: Franquia | E14: 0 | F14: 0 | G14: Condicional | H14: Licence Farma | I14: 25 mil solicitações/mês; 500/dia por IP
A15: OCR | B15: OCR.space | C15: Pro | D15: Mensal | E15: 30 | F15: 151.91 | G15: Opcional | H15: Licence Farma | I15: 300 mil solicitações mensais
A16: Mapas | B16: Google Maps | C16: APIs | D16: Por uso | G16: Condicional | H16: Licence Farma | I16: Configurar orçamento, alertas e limites
A17: Pagamento | B17: Mercado Pago | C17: Taxa por transação | D17: Por venda | G17: Sim, se habilitado | H17: Loja | I17: Varia conforme meio de pagamento e prazo de recebimento
A18: Marketplace | B18: Mercado Livre | C18: Comissão e frete | D18: Por venda | G18: Não | H18: Loja | I18: Varia conforme categoria e tipo de anúncio
A19: Domínio | B19: Registro .com.br | C19: Renovação | D19: Anual | G19: Sim | H19: Licence Farma | I19: Preencher o valor real da fatura
A20: Operação | B20: Entrega | C20: Motoboy ou parceiro | D20: Por entrega ou mensal | G20: Condicional | H20: Loja | I20: Definir custo, raio e repasse
A21: Operação | B21: Suporte | C21: Equipe humana | D21: Mensal | G21: Sim | H21: Licence Farma e loja | I21: Separar atendimento de níveis 1, 2 e 3
A22: Marketing | B22: Mídia e criação | C22: Campanhas | D22: Mensal variável | G22: Não | H22: Licence Farma e loja | I22: Definir orçamento por região

Sheet Estimativa IA
A1: Estimativa de inteligência artificial
A2: Edite a quantidade mensal para simular o custo. Valores são estimativas técnicas.
A4: Recurso | B4: Chamadas/mês | C4: Tokens entrada | D4: Tokens saída | E4: US$/M entrada | F4: US$/M saída | G4: Custo US$ | H4: Custo R$
A5: Busca inteligente | B5: 2000 | C5: 700 | D5: 400 | E5: 1 | F5: 5 | G5: =B5*((C5/1000000)*E5+(D5/1000000)*F5) | H5: =G5*Resumo!$B$5
A6: Suporte com IA | B6: 300 | C6: 1000 | D6: 500 | E6: 1 | F6: 5 | G6: =B6*((C6/1000000)*E6+(D6/1000000)*F6) | H6: =G6*Resumo!$B$5
A7: Cross-sell | B7: 100 | C7: 2500 | D7: 300 | E7: 1 | F7: 5 | G7: =B7*((C7/1000000)*E7+(D7/1000000)*F7) | H7: =G7*Resumo!$B$5
A8: Personalização curta | B8: 500 | C8: 300 | D8: 80 | E8: 1 | F8: 5 | G8: =B8*((C8/1000000)*E8+(D8/1000000)*F8) | H8: =G8*Resumo!$B$5
A9: Descrição de produto | B9: 500 | C9: 500 | D9: 320 | E9: 1 | F9: 5 | G9: =B9*((C9/1000000)*E9+(D9/1000000)*F9) | H9: =G9*Resumo!$B$5
A10: Visão de receita/embalagem | B10: 50 | C10: 3000 | D10: 200 | E10: 3 | F10: 15 | G10: =B10*((C10/1000000)*E10+(D10/1000000)*F10) | H10: =G10*Resumo!$B$5
A11: TOTAL | G11: =SUM(G5:G10) | H11: =SUM(H5:H10)
